{"\u4e00":{"0":"","1":"[![](https:\/\/www.bing.com\/th?id=OHR.SyracuseItaly_ZH-CN1001695972_320x240.jpg \"\u9521\u62c9\u5e93\u8428\u7684\u65e5\u843d\uff0c\u897f\u897f\u91cc\u5c9b\uff0c\u610f\u5927\u5229\")](https:\/\/www.bing.com\/th?id=OHR.SyracuseItaly_ZH-CN1001695972_UHD.jpg)<br>0706<br>\u767e\u4ee3\u954c\u523b\u4e4b\u57ce","2":"[![](https:\/\/www.bing.com\/th?id=OHR.NavajoSandstone_ZH-CN5009673011_320x240.jpg \"\u7f9a\u7f8a\u5ce1\u8c37\uff0c\u7eb3\u74e6\u970d\u65cf\u4fdd\u7559\u5730\uff0c\u4e9a\u5229\u6851\u90a3\u5dde\uff0c\u7f8e\u56fd\")](https:\/\/www.bing.com\/th?id=OHR.NavajoSandstone_ZH-CN5009673011_UHD.jpg)<br>0713<br>\u4e3a\u6447\u6eda\u800c\u751f","3":"[![](https:\/\/www.bing.com\/th?id=OHR.Artemis_ZH-CN3540365575_320x240.jpg \"\u6708\u7403\u4e0e\u5730\u7403\u7531\u963f\u8033\u5fd2\u5f25\u65af2\u53f7\u673a\u7ec4\u4eba\u5458\u62cd\u6444\")](https:\/\/www.bing.com\/th?id=OHR.Artemis_ZH-CN3540365575_UHD.jpg)<br>0720<br>\u6708\u77b0\u5bf0\u5b87","4":""},"\u4e8c":{"0":"","1":"[![](https:\/\/www.bing.com\/th?id=OHR.MountainToucanOrchids_ZH-CN1400221431_320x240.jpg \"\u677f\u5634\u5c71\u5de8\u5634\u9e1f\u4e0e\u5170\u82b1\uff0c\u5384\u74dc\u591a\u5c14\")](https:\/\/www.bing.com\/th?id=OHR.MountainToucanOrchids_ZH-CN1400221431_UHD.jpg)<br>0707<br>\u6797\u51a0\u534e\u5f69","2":"[![](https:\/\/www.bing.com\/th?id=OHR.LemonShark_ZH-CN4650331008_320x240.jpg \"\u67e0\u6aac\u9ca8\u5e7c\u5d3d\u5728\u7ea2\u6811\u6797\u4e2d\uff0c\u4f0a\u67f3\u585e\u62c9\u5c9b\uff0c\u5df4\u54c8\u9a6c\")](https:\/\/www.bing.com\/th?id=OHR.LemonShark_ZH-CN4650331008_UHD.jpg)<br>0714<br>\u5947\u5999\u7684\u771f\u76f8","3":"[![](https:\/\/www.bing.com\/th?id=OHR.SantaCatalina_ZH-CN6223370790_320x240.jpg \"\u5723\u5361\u5854\u7433\u5a1c\u62f1\u95e8\uff0c\u5b89\u63d0\u74dc\uff0c\u5371\u5730\u9a6c\u62c9\")](https:\/\/www.bing.com\/th?id=OHR.SantaCatalina_ZH-CN6223370790_UHD.jpg)<br>0721<br>\u62f1\u5f71\u5bfb\u8e2a","4":""},"\u4e09":{"0":"[![](https:\/\/www.bing.com\/th?id=OHR.DungeonPark_ZH-CN9544093701_320x240.jpg \"\u5730\u7262\u7701\u7acb\u516c\u56ed, \u7ebd\u82ac\u5170\u548c\u62c9\u5e03\u62c9\u591a\u7701, \u52a0\u62ff\u5927\")](https:\/\/www.bing.com\/th?id=OHR.DungeonPark_ZH-CN9544093701_UHD.jpg)<br>0701<br>\u5927\u897f\u6d0b\u96d5\u7422\u800c\u6210\u7684\u52a0\u62ff\u5927","1":"[![](https:\/\/www.bing.com\/th?id=OHR.LakeAtitlan_ZH-CN1920221893_320x240.jpg \"\u963f\u8482\u7279\u5170\u6e56\u7684\u65e5\u51fa\uff0c\u5371\u5730\u9a6c\u62c9\")](https:\/\/www.bing.com\/th?id=OHR.LakeAtitlan_ZH-CN1920221893_UHD.jpg)<br>0708<br>\u8fdc\u53e4\u706b\u5c71\u7684\u56de\u54cd","2":"[![](https:\/\/www.bing.com\/th?id=OHR.MarieLake_ZH-CN4927917413_320x240.jpg \"\u739b\u4e3d\u6e56\uff0c\u7ea6\u7ff0\u00b7\u7f2a\u5c14\u8352\u91ce\uff08\u6bd5\u6653\u666e\u9644\u8fd1\uff09\uff0c\u52a0\u5229\u798f\u5c3c\u4e9a\u5dde\uff0c\u7f8e\u56fd\")](https:\/\/www.bing.com\/th?id=OHR.MarieLake_ZH-CN4927917413_UHD.jpg)<br>0715<br>\u6500\u767b\u540e\u7684\u5956\u52b1","3":"","4":""},"\u56db":{"0":"[![](https:\/\/www.bing.com\/th?id=OHR.TempleEsna_ZH-CN9834689523_320x240.jpg \"\u57c3\u65af\u7eb3\u795e\u5e99\u7a79\u9876\u5929\u82b1\u677f, \u57c3\u53ca\")](https:\/\/www.bing.com\/th?id=OHR.TempleEsna_ZH-CN9834689523_UHD.jpg)<br>0702<br>\u8d70\u8fdb\u57c3\u65af\u7eb3\u795e\u5723\u7684\u4e16\u754c","1":"[![](https:\/\/www.bing.com\/th?id=OHR.SapaVietnam_ZH-CN2178893672_320x240.jpg \"\u5728\u6c99\u5df4\u7684\u6c34\u7a3b\u7530\uff0c\u8001\u8857\uff0c\u8d8a\u5357\")](https:\/\/www.bing.com\/th?id=OHR.SapaVietnam_ZH-CN2178893672_UHD.jpg)<br>0709<br>\u6b65\u6b65\u4f20\u627f","2":"[![](https:\/\/www.bing.com\/th?id=OHR.NavyPier_ZH-CN4649271588_320x240.jpg \"\u6d77\u519b\u7801\u5934\uff0c\u829d\u52a0\u54e5\uff0c\u4f0a\u5229\u8bfa\u4f0a\u5dde\uff0c\u7f8e\u56fd\")](https:\/\/www.bing.com\/th?id=OHR.NavyPier_ZH-CN4649271588_UHD.jpg)<br>0716<br>\u6ee8\u6c34\u53d8\u8272\u9f99","3":"","4":""},"\u4e94":{"0":"[![](https:\/\/www.bing.com\/th?id=OHR.FirefliesJapan_ZH-CN0071253415_320x240.jpg \"\u5c0f\u6eaa\u4e0a\u65b9\u7684\u8424\u706b\u866b\uff0c\u5188\u5c71\u53bf\uff0c\u65e5\u672c\")](https:\/\/www.bing.com\/th?id=OHR.FirefliesJapan_ZH-CN0071253415_UHD.jpg)<br>0703<br>\u6d41\u5149\u4e4b\u8bd7","1":"[![](https:\/\/www.bing.com\/th?id=OHR.VictoriaBeach_ZH-CN8892195426_320x240.jpg \"\u9646\u5730\u4e0e\u6d77\u6d0b\u7684\u9e1f\u77b0\u56fe\uff0c\u7ef4\u591a\u5229\u4e9a\u5dde\uff0c\u6fb3\u5927\u5229\u4e9a\")](https:\/\/www.bing.com\/th?id=OHR.VictoriaBeach_ZH-CN8892195426_UHD.jpg)<br>0710<br>\u9646\u5730\u4e0e\u6d77\u6d0b\u7684\u9e1f\u77b0\u56fe","2":"[![](https:\/\/www.bing.com\/th?id=OHR.VaiUmbrellas_ZH-CN1271422272_320x240.jpg \"\u74e6\u4f0a\u6d77\u6ee9\u4e0a\u7684\u65e5\u5149\u6d74\u8eba\u6905\uff0c\u514b\u91cc\u7279\u5c9b\uff0c\u5e0c\u814a\")](https:\/\/www.bing.com\/th?id=OHR.VaiUmbrellas_ZH-CN1271422272_UHD.jpg)<br>0717<br>\u5e0c\u814a\u5f0f\u7684\u9003\u79bb","3":"","4":""},"\u516d":{"0":"[![](https:\/\/www.bing.com\/th?id=OHR.KaysersbergVillage_ZH-CN0445080679_320x240.jpg \"\u51ef\u6cfd\u65af\u5821\uff0c\u963f\u5c14\u8428\u65af\uff0c\u6cd5\u56fd\")](https:\/\/www.bing.com\/th?id=OHR.KaysersbergVillage_ZH-CN0445080679_UHD.jpg)<br>0704<br>\u6b64\u884c\uff0c\u4e0d\u865a\u7ed5\u9053","1":"[![](https:\/\/www.bing.com\/th?id=OHR.AurayBrittany_ZH-CN5549157888_320x240.jpg \"\u5723\u53e4\u65af\u5766\u6e2f, \u6b27\u8d56, \u5e03\u5217\u5854\u5c3c, \u6cd5\u56fd\")](https:\/\/www.bing.com\/th?id=OHR.AurayBrittany_ZH-CN5549157888_UHD.jpg)<br>0711<br>\u5e03\u5217\u5854\u5c3c\u7684\u6f6e\u6c50\u4e4b\u7ea6","2":"[![](https:\/\/www.bing.com\/th?id=OHR.DevilsBridge_ZH-CN2164982440_320x240.jpg \"\u6076\u9b54\u6865\u5728\u514b\u7f57\u59c6\u52b3\u675c\u9e43\u82b1\u516c\u56ed\uff0c\u8428\u514b\u68ee\u5dde\uff0c\u5fb7\u56fd\")](https:\/\/www.bing.com\/th?id=OHR.DevilsBridge_ZH-CN2164982440_UHD.jpg)<br>0718<br>\u73af\u5f71\u5706\u6210","3":"","4":""},"\u65e5":{"0":"[![](https:\/\/www.bing.com\/th?id=OHR.LavenderRows_ZH-CN0676810895_320x240.jpg \"\u74e6\u6717\u7d22\u52d2\u9ad8\u539f\u7684\u85b0\u8863\u8349\u884c\uff0c\u666e\u7f57\u65fa\u65af\uff0c\u6cd5\u56fd\")](https:\/\/www.bing.com\/th?id=OHR.LavenderRows_ZH-CN0676810895_UHD.jpg)<br>0705<br>\u7d2b\u8272\u82b1\u6d77","1":"[![](https:\/\/www.bing.com\/th?id=OHR.KatahdinWWNM_ZH-CN5496444375_320x240.jpg \"\u5361\u5854\u4e01\u68ee\u6797\u548c\u6c34\u57df\u56fd\u5bb6\u7eaa\u5ff5\u5730\uff0c\u7f05\u56e0\u5dde\uff0c\u7f8e\u56fd\")](https:\/\/www.bing.com\/th?id=OHR.KatahdinWWNM_ZH-CN5496444375_UHD.jpg)<br>0712<br>\u7f05\u56e0\u5dde\u7684\u72c2\u91ce\u4e00\u9762","2":"[![](https:\/\/www.bing.com\/th?id=OHR.HirundoRustica_ZH-CN2798518247_320x240.jpg \"\u4e0d\u540c\u4e9a\u79cd\u7684\u5bb6\u71d5\u805a\u5728\u4e00\u8d77\u4f11\u606f\")](https:\/\/www.bing.com\/th?id=OHR.HirundoRustica_ZH-CN2798518247_UHD.jpg)<br>0719<br>\u655b\u7fbd\u6816\u65f6","3":"","4":""}}